message_flow-0.3.7.dist-info/METADATA
message_flow-0.3.7.dist-info/WHEEL
message_flow-0.3.7.dist-info/entry_points.txt
message_flow-0.3.7.dist-info/licenses/LICENSE
message_flow/__init__.py
message_flow/__main__.py
message_flow/app/__init__.py
message_flow/app/__init__.pyi
message_flow/app/_fast_api.py
message_flow/app/_internal/__init__.py
message_flow/app/_internal/__init__.pyi
message_flow/app/_internal/async_api_studio/__init__.py
message_flow/app/_internal/async_api_studio/__init__.pyi
message_flow/app/_internal/async_api_studio/config.py
message_flow/app/_internal/async_api_studio/page.py
message_flow/app/_internal/channels.py
message_flow/app/_internal/message_flow_schema.py
message_flow/app/_message_management/__init__.py
message_flow/app/_message_management/__init__.pyi
message_flow/app/_message_management/dispatcher.py
message_flow/app/_message_management/producer.py
message_flow/app/_message_management/routing_headers.py
message_flow/app/_simple_messaging/__init__.py
message_flow/app/_simple_messaging/__init__.pyi
message_flow/app/_simple_messaging/simple_consumer.py
message_flow/app/_simple_messaging/simple_producer.py
message_flow/app/base_middleware.py
message_flow/app/message_flow.py
message_flow/app/messaging/__init__.py
message_flow/app/messaging/__init__.pyi
message_flow/app/messaging/consumer.py
message_flow/app/messaging/producer.py
message_flow/channel/__init__.py
message_flow/channel/__init__.pyi
message_flow/channel/_internal/__init__.py
message_flow/channel/_internal/__init__.pyi
message_flow/channel/_internal/channel_construction.py
message_flow/channel/_internal/channel_info.py
message_flow/channel/_internal/channel_schema.py
message_flow/channel/channel.py
message_flow/cli/__init__.py
message_flow/cli/__init__.pyi
message_flow/cli/_cli_app.py
message_flow/cli/_documentation_server.py
message_flow/cli/_logging_level.py
message_flow/cli/entrypoint.py
message_flow/message/__init__.py
message_flow/message/__init__.pyi
message_flow/message/_internal/__init__.py
message_flow/message/_internal/__init__.pyi
message_flow/message/_internal/message_construction.py
message_flow-0.3.7.dist-info/RECORD
