Metadata-Version: 2.1
Name: message-flow
Version: 0.3.7
Summary: Asynchronous Communication Framework
Author-Email: Valentin Vorobyev <voro6yov.valentin@gmail.com>
License: Apache License 2.0
Requires-Python: >=3.10
Requires-Dist: pydantic>=2.5.2
Requires-Dist: typer>=0.9.0
Requires-Dist: message-flow-rabbitmq>=0.2.2; extra == "rabbitmq"
Provides-Extra: rabbitmq
